svd2vec/__init__.py
svd2vec/core.py
svd2vec/files_io.py
svd2vec/temporary_array.py
svd2vec/utils.py
svd2vec/window.py
svd2vec/datasets/analogies/msr.txt
svd2vec/datasets/analogies/questions-words.txt
svd2vec/datasets/similarities/men_dataset.txt
svd2vec/datasets/similarities/mturk.txt
svd2vec/datasets/similarities/rarewords.txt
svd2vec/datasets/similarities/simlex999.txt
svd2vec/datasets/similarities/wordsim353.txt
svd2vec-0.3.3.dist-info/METADATA
svd2vec-0.3.3.dist-info/WHEEL
svd2vec-0.3.3.dist-info/top_level.txt
svd2vec-0.3.3.dist-info/RECORD
