Metadata-Version: 2.1
Name: svd2vec
Version: 0.3.3
Summary: A library that converts words to vectors using PMI and SVD
Home-page: https://github.com/valentinp72/svd2vec
Author: Valentin Pelloin
Author-email: valentin.pelloin.etu@univ-lemans.fr
License: MIT
Platform: UNKNOWN
Classifier: Programming Language :: Python :: 3
Classifier: License :: OSI Approved :: MIT License
Classifier: Operating System :: OS Independent
Requires-Dist: Pympler (>=0.7)
Requires-Dist: joblib (>=0.11)
Requires-Dist: numpy (>=1.16.4)
Requires-Dist: pandas (>=0.24.2)
Requires-Dist: scipy (>=1.0.0)
Requires-Dist: setuptools (>=46.1.3)
Requires-Dist: tqdm (>=4.45.0)
